{
  "file_path": "C:\\Users\\Haroldo Duraes\\Desktop\\Firmesa\\Comparativo ERP.xlsx",
  "text_content": "| Sistema        | Faixa de PreÃ§o                                                                                                                                  | Link Oficial                        | EspecializaÃ§Ã£o                                                                           | IntegraÃ§Ã£o                                                                                    | Usabilidade                                                               | Suporte                                                                           | Custo                                                                          | Escalabilidade\nADVTEC | Start: R$Â 499/mÃªs (1 usuÃ¡rio); Pro: R$Â 599/mÃªs (5 usuÃ¡rios); Platinum: R$Â 999/mÃªs (10 usuÃ¡rios) | advtec.com.br | ğŸŸ¢ Otimizado p/ hortifrÃºti (apps para pedidos, separaÃ§Ã£o, etc) | ğŸŸ¢ MÃ³dulos e apps integrados (vendas, estoque, compras) | ğŸŸ¢ Foco em simplicidade e rÃ¡pida implantaÃ§Ã£o (treinamentos em vÃ­deo) | ğŸŸ¢ Suporte imediato (WhatsApp, remoto) | ğŸŸ¡ Moderado (plano Pro equivale ~R$120/usuÃ¡rio/mÃªs) | ğŸŸ¡ Escala atÃ© mÃ©dio porte (20+ usuÃ¡rios; cloud)\nMercatus | Sob consulta (plano personalizado via fornecedor; preÃ§o nÃ£o divulgado publicamente) | mercatustecnologia.com.br | ğŸŸ¢ Especializado em distribuidores de alimentos (30+ anos no setor hortifrÃºti) | ğŸŸ¢ ERP integrado â€œAPP Ceasaâ€ (mÃ³dulos compras, estoque, vendas integrados) | ğŸŸ¡ Interface tradicional; possui apps mÃ³veis complementares | ğŸŸ¢ Suporte prÃ³ximo e especializado no segmento (equipe com experiÃªncia em Ceasas) | ğŸŸ¡ MÃ©dio/Alto (soluÃ§Ã£o robusta e consolidada â€“ investimento maior) | ğŸŸ¡ Escala de mÃ©dio porte (foca em atacadistas regionais; hÃ¡ casos de sucesso no setor)\nWebMais | Planos a partir de ~R$Â 250/mÃªs (Planos Ouro, Platina, Diamante; valor varia conforme usuÃ¡rios e mÃ³dulos) | webmaissistemas.com.br | ğŸŸ¢ Focado em indÃºstrias e distribuidoras (versÃ£o para hortifrÃºti disponÃ­vel) | ğŸŸ¡ ERP 100% online, integra setores bÃ¡sicos (financeiro, vendas, etc.) | ğŸŸ¢ Sistema online de fÃ¡cil acesso (interface web moderna) | ğŸŸ¢ Suporte via web/portal (empresa voltada a PMEs) | ğŸŸ¢ Baixo custo (modelo SaaS acessÃ­vel para pequenos e mÃ©dios) | ğŸŸ¡ Escalabilidade limitada a portes mÃ©dios (expansÃ£o conforme planos)\nNeXT Software | Profissional: R$Â 79/mÃªs (ERP local c/ PDV, 1 usuÃ¡rio); Enterprise: R$Â 99/mÃªs (ERP completo c/ Web, 1 usuÃ¡rio) â€“ +R$Â 15-20 por usuÃ¡rio adicional | nextsoftware.com.br (Hortifruti) | ğŸŸ¢ VersÃ£o ERP Hortifruti dedicada (10+ anos no setor) | ğŸŸ¡ IntegraÃ§Ã£o bÃ¡sica; inclui PDV, NF-e/NFC-e e atÃ© marketplace (Mercado Livre) | ğŸŸ¢ Interface simples com atalhos (voltada a pequenas empresas) | ğŸŸ¢ Suporte via helpdesk, chat e tutoriais online (focado em PME) | ğŸŸ¢ Muito baixo (planos sem fidelidade e baixo custo de entrada) | ğŸ”´ Baixa â€“ ideal para pequeno porte; pode nÃ£o suportar expansÃ£o grande (limitaÃ§Ãµes de arquitetura e base local nos planos bÃ¡sicos)\nLimber | Sob consulta (ERP modular, planos conforme segmento e porte da empresa) | limbersoftware.com.br | ğŸŸ¡ ERP agro e varejo com mÃ³dulo hortifrÃºti (Limber Agro) | ğŸŸ¢ IntegraÃ§Ã£o de processos operacionais e mobile (vendas, coleta, etc) | ğŸŸ¡ Interface corporativa (ERP amplo para diversos segmentos) | ğŸŸ¡ Suporte dedicado por segmento (atua com consultoria em agronegÃ³cio) | ğŸŸ¡ Custo mÃ©dio (soluÃ§Ã£o enterprise adaptada a PME e grandes) | ğŸŸ¡ Alta escalabilidade (foco em eficiÃªncia para empresas de vÃ¡rios portes)\nWLE Solutio | Sob consulta (licenciamento conforme mÃ³dulos e usuÃ¡rios) | wlesoft.com.br â€“ Solutio Hortifruti | ğŸŸ¢ ERP Solutio Hortifruti especializado (frutas, verduras, FLV) | ğŸŸ¢ IntegraÃ§Ã£o de processos do fornecedor Ã  distribuiÃ§Ã£o; integra balanÃ§as e conversÃ£o unidade | ğŸŸ¡ Sistema desktop com mÃ³dulos ricos (possui app mÃ³vel para pedidos) | ğŸŸ¢ Suporte regional especializado (foco no sul; atendimento telefÃ´nico e in loco) | ğŸŸ¡ Custo mÃ©dio (soluÃ§Ã£o nichada, personalizÃ¡vel) | ğŸŸ¡ Escala para mÃ©dio porte (atende frutarias e distribuidoras regionais)\nTOTVS Consinco | Sob consulta (licenÃ§a e serviÃ§os customizados â€“ soluÃ§Ã£o enterprise) | consinco.com.br | ğŸŸ¡ ERP de varejo/distribuiÃ§Ã£o amplo (linha Consinco, supermercados e atacado) | ğŸŸ¢ AltÃ­ssima integraÃ§Ã£o (ERP + WMS + PDV; mÃºltiplos mÃ³dulos e apps TOTVS) | ğŸ”´ Complexidade elevada (muitas funcionalidades; exige treinamento) | ğŸŸ¡ Suporte TOTVS (rede nacional, porÃ©m menos Ã¡gil para PME) | ğŸ”´ Alto custo (soluÃ§Ã£o robusta para grandes redes; investimento significativo) | ğŸŸ¢ AltÃ­ssima â€“ atende grandes atacadistas e redes varejistas (escalÃ¡vel para qualquer porte)\nBluesoft | A partir de ~US$Â 5.000/mÃªs (â‰ˆR$Â 25 mil) segundo Capterra (modelo 100% SaaS na nuvem) | bluesoft.com.br | ğŸŸ¡ ERP cloud para varejo e atacado (supermercados, distribuidoras de mÃ©dio-grande porte) | ğŸŸ¢ Forte integraÃ§Ã£o (API aberta; mÃ³dulos financeiros, logÃ­stica, fiscal integrados) | ğŸŸ¡ Interface web moderna, porÃ©m abrangente (pode ser complexa pelo porte) | ğŸŸ¡ Suporte dedicado a clientes enterprise (equipe especializada, TOTVS SA) | ğŸ”´ Elevado (focado em mÃ©dio/grande â€“ investimento alto mensal) | ğŸŸ¢ Alta â€“ soluÃ§Ã£o escalÃ¡vel para grandes volumes (SaaS em nuvem elÃ¡stica)\n| Sistema ERP            | EspecializaÃ§Ã£o no Setor                                                                                                                                                                                                         | AutomaÃ§Ã£o & IntegraÃ§Ã£o                                                                                                                                                                                                                                                                                      | Facilidade de Uso / ImplantaÃ§Ã£o                                                                                                                                                                                               | Suporte TÃ©cnico                                                                                                                                                                                                                       | Custo (Mensal)                                                                                                                                                                                           | Escalabilidade\nADVTEC Hortifruti | 100% focado em distribuidoras de hortifrÃºti (FLV). MÃ³dulos de vendas, compras, estoque, NF-e etc. jÃ¡ adaptados ao ramo. | Altamente automatizado, com mÃºltiplos apps mÃ³veis integrados (pedido de cliente, vendas, compras, picking, inventÃ¡rio). MÃ³dulos totalmente integrados (do pedido ao financeiro). | Interface intuitiva, com fluxos pensados para FLV. ImplantaÃ§Ã£o rÃ¡pida via SaaS; fornecedor fornece vÃ­deos de treinamento e ajuda na parametrizaÃ§Ã£o inicial. | Suporte imediato e humanizado â€“ contato direto via WhatsApp, acesso remoto e telefone. Atendimento Ã¡gil focado nos horÃ¡rios crÃ­ticos do setor. | Assinatura mensal (valores sob consulta). Custo acessÃ­vel para PME; personalizaÃ§Ãµes adicionais pagas Ã  parte. ROI alto com ganhos de eficiÃªncia. | Escala para pequeno e mÃ©dio porte. Suporta operaÃ§Ãµes fracionadas e atacado de FLV. Pode atender mÃºltiplos CDs regionais; para grandes redes, avaliar capacidade.\nMercatus APP Ceasa | Totalmente especializado em atacadistas/distribuidores de FLV, nasceu dentro da CEASA. Focado em vendas no atacado, boxes e distribuiÃ§Ã£o hortifrÃºti. | AutomaÃ§Ã£o elevada: apps mÃ³veis para forÃ§a de vendas (clientes fazem pedidos online) e contagem de estoque. IntegraÃ§Ã£o nativa com sistema Paripassu para rastreabilidade ANVISA. MÃ³dulos de estoque, vendas, financeiro integrados. | Sistema em nuvem de fÃ¡cil acesso. Aplicativos amigÃ¡veis para usuÃ¡rios e clientes. ImplantaÃ§Ã£o guiada pelo fornecedor; interface moderna e simplificada. | Suporte diferenciado, com horÃ¡rios estendidos incluindo madrugadas, fins de semana â€“ alinhado Ã  rotina de CEASA. Atendimento via telefone, WhatsApp, chat e ticket. | Assinatura mensal conforme mÃ³dulos. Investimento mÃ©dio; justificado pelas funcionalidades (BI, mobile) e suporte estendido. Sem custos de infraestrutura (100% cloud). | Altamente escalÃ¡vel: atende empresas em todo Brasil. Suporta crescimento de volume sem degradaÃ§Ã£o (infra AWS). Adequado a distribuidores regionais e nacionais de mÃ©dio a grande porte.\nWebMais ERP | ERP nacional para Distribuidoras, com versÃ£o focada em alimentos/hortifrÃºti. Inclui mÃ³dulos de estoque, expediÃ§Ã£o, vendas, compras e financeiro ajustados para perecÃ­veis. | Boa integraÃ§Ã£o entre setores, eliminando retrabalho. Controle de lote/validade integrado ao estoque/vendas. Possui app de vendas e relatÃ³rios de rotatividade, mas automaÃ§Ã£o de picking/logÃ­stica Ã© bÃ¡sica. | Interface web simples e em portuguÃªs. ImplementaÃ§Ã£o rÃ¡pida, com trial gratuito e suporte na migraÃ§Ã£o. Curva de aprendizado curta â€“ voltado a usuÃ¡rios de PME sem TI dedicada. | Suporte em horÃ¡rio comercial via telefone/chat. Equipe acessÃ­vel e prestativa, porÃ©m sem suporte 24h. DocumentaÃ§Ã£o e vÃ­deos tutoriais disponÃ­veis. | Planos mensais acessÃ­veis (hÃ¡ opÃ§Ã£o de teste grÃ¡tis). PreÃ§o varia por nÂº de usuÃ¡rios/mÃ³dulos, porÃ©m competitivo para pequenas e mÃ©dias empresas. | Escalabilidade moderada: ideal para pequenas e mÃ©dias distribuidoras. Suporta multi-filial e volumes razoÃ¡veis. Para expansÃ£o muito grande (vÃ¡rios depÃ³sitos, milhares de notas/dia), talvez demandaria upgrade para um ERP mais robusto.\nNeXT ERP Hortifruti | Desenvolvido especialmente para hortifrÃºti, com 10+ anos de melhorias no setor. Atende tanto lojas de hortifrÃºti quanto distribuidoras, com mÃ³dulos especÃ­ficos (cadastro de FLV, etc.). | Integra todos os mÃ³dulos bÃ¡sicos (compras-estoque-vendas-financeiro). EmissÃ£o ilimitada de NF-e/NFS-e. AutomaÃ§Ã£o razoÃ¡vel: gera duplicatas automaticamente, atualiza estoque em tempo real, etc., porÃ©m nÃ£o possui apps especializados (usa interface principal). | Sistema Ã¡gil e estÃ¡vel. ImplantaÃ§Ã£o guiada com suporte da equipe NeXT; disponibiliza demo online para facilidade. UI tradicional, mas simples. UsuÃ¡rios aprendem rÃ¡pido tarefas comuns (venda, pedido, entrada). | Suporte por telefone e chat em horÃ¡rio comercial. Equipe conhecedora do produto e do ramo, suporte personalizado para dÃºvidas fiscais/operacionais. AtualizaÃ§Ãµes frequentes para atender legislaÃ§Ã£o. | Mensalidade com Ã³timo custo-benefÃ­cio segundo o fornecedor. Faixas de preÃ§o para micro, pequena e mÃ©dia empresa, tornando viÃ¡vel a adesÃ£o de negÃ³cios familiares. | Escala para pequeno/mÃ©dio porte. Suporta vÃ¡rios usuÃ¡rios e filiais, mas Ã© limitado para operaÃ§Ãµes de grande porte. Permite crescimento orgÃ¢nico e aceita customizaÃ§Ãµes sob demanda se o cliente ampliar operaÃ§Ãµes.\nWLE Solutio Hortifruti | ERP verticalizado para hortifrÃºti, parte da suÃ­te Solutio. Atende do varejo ao atacado de FLV, contemplando peculiaridades (un. medida, balanÃ§as, perecÃ­veis). | Altamente integrado: mÃ³dulos de compras, WMS/estoque, vendas PDV ou pedidos, financeiro e fiscal num sÃ³ sistema. Rastreamento de lotes embutido; integraÃ§Ã£o com balanÃ§as e coletores de dados; emissÃ£o de CT-e, MDF-e para logÃ­stica. AutomaÃ§Ã£o de processos avanÃ§ada (OC automÃ¡tica, atualizaÃ§Ãµes online). | Sistema robusto, requer configuraÃ§Ã£o detalhada. ImplementaÃ§Ã£o mais longa, personalizada conforme o cliente (muitos parÃ¢metros). Interface rica em funÃ§Ãµes â€“ exige treinamento, porÃ©m fornece grande poder de gestÃ£o. | Suporte dedicado, com consultores especializados no segmento. Atendimento humanizado, via telefone/e-mail, com direito a melhorias contÃ­nuas e backups cloud. Rede de parceiros para suporte local. | Modelo de licenÃ§a ou assinatura modular. Custo mÃ©dio/alto, proporcional Ã  abrangÃªncia da soluÃ§Ã£o. Recomendado para quem busca investimento em controle total (ROI via reduÃ§Ã£o de perdas e eficiÃªncia). | AltÃ­ssima escalabilidade: versÃµes para vÃ¡rios portes (Basic atÃ© Enterprise). Suporta mÃºltiplos CDs, centenas de usuÃ¡rios e grande volume de dados. Preparado para operaÃ§Ãµes complexas e em expansÃ£o, com atualizaÃ§Ãµes constantes para longevidade.\nLimber ERP (Agro) | ERP nacional focado em eficiÃªncia para agronegÃ³cio e varejo. VersÃ£o hortifruti com funcionalidades dedicadas (estoque de perecÃ­veis, multi-estoques, etc.). Menos conhecido, mas especializado em melhorar gestÃ£o de FLV. | Boa integraÃ§Ã£o intersetorial: controle online de validade/lotes no estoque; mÃ³dulos de compras, estoque, vendas e financeiro unificados. Oferece requisÃ§Ã£o de compra automatizada, transferÃªncia entre estoques e inventÃ¡rio mÃ³vel. | Interface moderna e limpa, com menus por segmento. ImplantaÃ§Ã£o assistida â€“ consultoria inicial para configurar conforme necessidades. Uso intuitivo apÃ³s setup; foco em simplicidade para o usuÃ¡rio final. | Suporte via canais digitais e telefone. Empresa orientada a resultados do cliente â€“ acompanhamento prÃ³ximo. AtualizaÃ§Ãµes inclusas e infraestrutura cloud gerida pela Limber (menos preocupaÃ§Ã£o para TI do cliente). | Assinatura SaaS flexÃ­vel conforme mÃ³dulos e tamanho da empresa. Custo na faixa de ERPs cloud para PMEs; investimento se paga com ganho de controle (evitar perdas, otimizar estoque). | EscalÃ¡vel para vÃ¡rios portes: atende pequenos negÃ³cios atÃ© cooperativas e cerealistas, logo comporta distribuidoras mÃ©dias. Infraestrutura cloud ajusta recursos conforme crescimento. Pode integrar filiais e atender expansÃ£o regional sem troca de sistema.\nTOTVS (Consinco) | ERP consolidado para varejo/atacado alimentar. MÃ³dulos abrangentes que cobrem hortifrÃºti (compras especializadas, gestÃ£o de fornecedores agrÃ­colas, app de compras FLV). NÃ£o exclusivo de FLV, mas altamente aderente ao setor. | IntegraÃ§Ã£o completa e personalizÃ¡vel: todos os processos de negÃ³cio em uma plataforma Ãºnica. Elevada automaÃ§Ã£o: abastecimento automÃ¡tico de estoque, geraÃ§Ã£o nativa de indicadores, integraÃ§Ã£o com PDVs, logÃ­stica (rota, CT-e) e sistemas externos via API. | Sistema robusto e flexÃ­vel, mas complexo â€“ implementaÃ§Ã£o exige projeto estruturado e tempo. Interface profissional, requer treinamento intensivo de usuÃ¡rios-chave. Muito configurÃ¡vel Ã s regras especÃ­ficas de cada empresa. | Suporte estruturado (TOTVS e parceiros). Atendimento via portal com SLAs; possibilidade de suporte dedicado (AMS). AtualizaÃ§Ãµes frequentes garantem compliance legal. Comunidade grande de usuÃ¡rios TOTVS para troca de conhecimento. | Assinatura enterprise (pode rodar on-premise ou cloud). Custo elevado, adequando-se melhor a mÃ©dias/grandes empresas. Inclui acesso a todo ecossistema TOTVS (updates, suporte, evoluÃ§Ãµes tecnolÃ³gicas). | Escalabilidade mÃ¡xima: atende redes de qualquer porte sem perda de performance. Projetado para crescer junto com a empresa â€“ multi-filial, alta volumetria, ambientes complexos. Investimento de longo prazo, evitando futuras migraÃ§Ãµes.\n| Sistema                  | Faixa de PreÃ§o                                                                                        | Link Oficial                        | EspecializaÃ§Ã£o                                                                               | IntegraÃ§Ã£o                                                                                             | Usabilidade                                                                   | Suporte                                                                                   | Custo                                                                          | Escalabilidade\nADVTEC | Start: R$ 499/mÃªs (1 usuÃ¡rio)Pro: R$ 599/mÃªs (5 usuÃ¡rios)Platinum: R$ 999/mÃªs (10 usuÃ¡rios) | advtec.com.br | â­â­â­â­â­ Otimizado p/ hortifrÃºti (apps para pedidos, separaÃ§Ã£o, etc) | â­â­â­â­â­ MÃ³dulos e apps integrados (vendas, estoque, compras) | â­â­â­â­â­ Foco em simplicidade e rÃ¡pida implantaÃ§Ã£o (treinamentos em vÃ­deo) | â­â­â­â­â­ Suporte imediato (WhatsApp, remoto) | â­â­â­ Moderado (plano Pro equivale ~R$120/usuÃ¡rio/mÃªs) | â­â­â­ Escala atÃ© mÃ©dio porte (20+ usuÃ¡rios; cloud)\nMercatus (APP Ceasa) | Sob consulta (plano personalizado; preÃ§o nÃ£o divulgado) | mercatustecnologia.com.br | â­â­â­â­â­ Especializado em distribuidores de alimentos (30+ anos no setor hortifrÃºti) | â­â­â­â­â­ ERP integrado â€œAPP Ceasaâ€ (mÃ³dulos compras, estoque, vendas integrados) | â­â­â­â­ Interface tradicional; possui apps mÃ³veis complementares | â­â­â­â­â­ Suporte prÃ³ximo e especializado no segmento (equipe com experiÃªncia em CEASA) | â­â­â­ MÃ©dio/Alto (soluÃ§Ã£o robusta e consolidada â€“ investimento maior) | â­â­â­ Escala de mÃ©dio porte (foca em atacadistas regionais; hÃ¡ casos de sucesso no setor)\nWebMais | A partir de ~R$ 250/mÃªs (planos Ouro, Platina, Diamante) | webmaissistemas.com.br | â­â­â­â­â­ Focado em indÃºstrias e distribuidoras (versÃ£o para hortifrÃºti disponÃ­vel) | â­â­â­ ERP 100% online, integra setores bÃ¡sicos (financeiro, vendas, etc.) | â­â­â­â­â­ Sistema online de fÃ¡cil acesso (interface web moderna) | â­â­â­â­â­ Suporte via web/portal (empresa voltada a PMEs) | â­â­â­â­â­ Baixo custo (modelo SaaS acessÃ­vel para pequenos e mÃ©dios) | â­â­â­ Escalabilidade limitada a portes mÃ©dios (expansÃ£o conforme planos)\nNeXT Software | Profissional: R$ 79/mÃªs (1 usuÃ¡rio)Enterprise: R$ 99/mÃªs (1 usuÃ¡rio) + R$ 15â€“20 por usuÃ¡rio adicional | nextsoftware.com.br | â­â­â­â­â­ VersÃ£o ERP Hortifruti dedicada (10+ anos no setor) | â­â­â­ IntegraÃ§Ã£o bÃ¡sica; inclui PDV, NF-e/NFC-e e atÃ© marketplace (Mercado Livre) | â­â­â­â­â­ Interface simples com atalhos (voltada a pequenas empresas) | â­â­â­â­â­ Suporte via helpdesk, chat e tutoriais online (focado em PME) | â­â­â­â­â­ Muito baixo (planos sem fidelidade e baixo custo de entrada) | â­ Baixa â€“ ideal para pequeno porte; pode nÃ£o suportar expansÃ£o grande (limitaÃ§Ãµes de arquitetura e base local nos planos bÃ¡sicos)\nLimber ERP | Sob consulta (planos modulares conforme porte/segmento) | limbersoftware.com.br | â­â­â­ ERP agro e varejo com mÃ³dulo hortifrÃºti (Limber Agro) | â­â­â­â­â­ IntegraÃ§Ã£o de processos operacionais e mobile (vendas, coleta, etc) | â­â­â­ Interface corporativa (ERP amplo para diversos segmentos) | â­â­â­ Suporte dedicado por segmento (atua com consultoria em agronegÃ³cio) | â­â­â­ Custo mÃ©dio (soluÃ§Ã£o enterprise adaptada a PME e grandes) | â­â­â­ Alta escalabilidade (foco em eficiÃªncia para empresas de vÃ¡rios portes)\nWLE Solutio (Hortifruti) | Sob consulta (licenciamento modular conforme usuÃ¡rios/mÃ³dulos) | wlesoft.com.br â€“ Solutio Hortifruti | â­â­â­â­â­ ERP Solutio Hortifruti especializado (frutas, verduras, FLV) | â­â­â­â­â­ IntegraÃ§Ã£o de processos do fornecedor Ã  distribuiÃ§Ã£o ; integra balanÃ§as e conversÃ£o unidade | â­â­â­ Sistema desktop com mÃ³dulos ricos (possui app mÃ³vel para pedidos) | â­â­â­â­â­ Suporte regional especializado (foco no Sul; atendimento telefÃ´nico e in loco) | â­â­â­ Custo mÃ©dio (soluÃ§Ã£o nichada, personalizÃ¡vel) | â­â­â­ Escala para mÃ©dio porte (atende frutarias e distribuidoras regionais)\nTOTVS (Consinco) | Sob consulta (licenÃ§a e serviÃ§os customizados; soluÃ§Ã£o enterprise) | consinco.com.br | â­â­â­ ERP de varejo/distribuiÃ§Ã£o amplo (linha Consinco, supermercados e atacado) | â­â­â­â­â­ AltÃ­ssima integraÃ§Ã£o (ERP + WMS + PDV; mÃºltiplos mÃ³dulos e apps TOTVS) | â­ Complexidade elevada (muitas funcionalidades; exige treinamento) | â­â­â­ Suporte TOTVS (rede nacional, porÃ©m menos Ã¡gil para PME) | â­ Alto custo (soluÃ§Ã£o robusta para grandes redes; investimento significativo) | â­â­â­â­â­ AltÃ­ssima â€“ atende grandes atacadistas e redes varejistas (escalÃ¡vel para qualquer porte)\nBluesoft | A partir de ~US$ 5.000/mÃªs (~R$ 25 000/mÃªs) | bluesoft.com.br | â­â­â­ ERP cloud para varejo e atacado (supermercados, distribuidoras de mÃ©dio-grande porte) | â­â­â­â­â­ Forte integraÃ§Ã£o (API aberta; mÃ³dulos financeiros, logÃ­stica, fiscal integrados) | â­â­â­ Interface web moderna, porÃ©m abrangente (pode ser complexa pelo porte) | â­â­â­ Suporte dedicado a clientes enterprise (equipe especializada TOTVS SA) | â­ Elevado (focado em mÃ©dio/grande â€“ investimento alto mensal) | â­â­â­â­â­ Alta â€“ soluÃ§Ã£o escalÃ¡vel para grandes volumes (SaaS em nuvem elÃ¡stica)\n| Sistema                | Link Oficial              | Faixa de PreÃ§o                                       | EspecializaÃ§Ã£o                                    | IntegraÃ§Ã£o                                      | Usabilidade                           | Suporte                                        | Custo                                  | Escalabilidade                         | InovaÃ§Ã£o TecnolÃ³gica\nADVTEC | advtec.com.br | Start: R$ 399/mÃªsPro: R$ 599/mÃªsPlatinum: R$ 999/mÃªs | â˜…â˜…â˜…â˜…â˜… (Foco 100 % em hortifrÃºti, apps exclusivos) | â˜…â˜…â˜…â˜…â˜† (NF-e, balanÃ§as, integraÃ§Ãµes padrÃµes) | â˜…â˜…â˜…â˜…â˜… (Muito intuitivo, mobile-first) | â˜…â˜…â˜…â˜…â˜… (Suporte imediato via WhatsApp) | â˜…â˜…â˜…â˜…â˜† (PreÃ§o acessÃ­vel) | â˜…â˜…â˜…â˜…â˜† (Cresce bem para PMEs, cloud) | â˜…â˜…â˜…â˜…â˜… (IA em pedidos, suite mobile completa)\nMercatus (APP Ceasa) | mercatustecnologia.com.br | Sob consulta (plano personalizado) | â˜…â˜…â˜…â˜…â˜… (30 anos no setor FLV, recursos Ceasa) | â˜…â˜…â˜…â˜…â˜… (MÃ³dulos integrados, Paripassu, bancÃ¡ria) | â˜…â˜…â˜…â˜…â˜† (Sistema robusto, apps ajudam) | â˜…â˜…â˜…â˜…â˜… (Suporte estendido em horÃ¡rios crÃ­ticos) | â˜…â˜…â˜…â˜†â˜† (Investimento mÃ©dio/alto) | â˜…â˜…â˜…â˜…â˜† (Escala para mÃ©dias, cloud) | â˜…â˜…â˜…â˜…â˜† (BI, mobile, rastreabilidade)\nHortiGestÃ£o | hortigestao.com.br | Planos a partir de ~R$ 299/mÃªs | â˜…â˜…â˜…â˜…â˜… (Nativo de CEASA, rotina FLV) | â˜…â˜…â˜…â˜…â˜† (NF-e, boletos, bÃ¡sico contÃ¡bil) | â˜…â˜…â˜…â˜…â˜… (Fluxo otimizado, app fÃ¡cil) | â˜…â˜…â˜…â˜…â˜… (Suporte 24 h, proximidade) | â˜…â˜…â˜…â˜…â˜† (SaaS, bom custo-benefÃ­cio) | â˜…â˜…â˜…â˜…â˜† (Cloud puro, multiusuÃ¡rio) | â˜…â˜…â˜…â˜…â˜† (App mÃ³vel, relatÃ³rios inteligentes)\nPOST Sistemas | postsistemas.com.br | Sob consulta (modular) | â˜…â˜…â˜…â˜…â˜† (ERP multi-segmento com mÃ³dulo FLV) | â˜…â˜…â˜…â˜…â˜… (Paripassu, TEF, NF-e, contÃ¡bil) | â˜…â˜…â˜…â˜…â˜† (Interface tradicional + apps) | â˜…â˜…â˜…â˜…â˜… (Suporte dedicado, melhorias) | â˜…â˜…â˜…â˜†â˜† (Modular, varia conforme extras) | â˜…â˜…â˜…â˜…â˜… (Altamente escalÃ¡vel) | â˜…â˜…â˜…â˜…â˜† (ForÃ§a de vendas/compras mobile, rastreabilidade)\nWLE Solutio Hortifruti | wlesoft.com.br | Sob consulta (licenciamento modular) | â˜…â˜…â˜…â˜…â˜† (ERP moldÃ¡vel para FLV e varejo) | â˜…â˜…â˜…â˜…â˜… (Integr. balanÃ§as, SAT, NF-e, contÃ¡bil) | â˜…â˜…â˜…â˜…â˜† (Uso simples, PDV integrado) | â˜…â˜…â˜…â˜…â˜† (Suporte regional, parceiros locais) | â˜…â˜…â˜…â˜…â˜† (Modular, custo mÃ©dio) | â˜…â˜…â˜…â˜…â˜† (Bom para pequenas e mÃ©dias) | â˜…â˜…â˜…â˜…â˜† (Etiquetagem, mobile inventory)\nLimber Agro | limbersoftware.com.br | Sob consulta (plano modular) | â˜…â˜…â˜…â˜…â˜† (AgronegÃ³cio + mÃ³dulo FLV) | â˜…â˜…â˜…â˜…â˜… (Cadeias agrÃ­colas, BI, IoT) | â˜…â˜…â˜…â˜†â˜† (Exige capacitaÃ§Ã£o) | â˜…â˜…â˜…â˜…â˜† (Suporte completo, consultoria) | â˜…â˜…â˜†â˜†â˜† (Custo elevado, foco enterprise) | â˜…â˜…â˜…â˜…â˜… (Nuvem escalÃ¡vel, grande volume) | â˜…â˜…â˜…â˜…â˜… (RoteirizaÃ§Ã£o automÃ¡tica, IA)",
  "sheets_data": {
    "Comparativo 1": [
      {
        "sheet_name": "Comparativo 1",
        "rows": 10,
        "columns": 9,
        "column_names": [
          "Sistema",
          "Faixa de PreÃ§o",
          "Link Oficial",
          "EspecializaÃ§Ã£o",
          "IntegraÃ§Ã£o",
          "Usabilidade",
          "Suporte",
          "Custo",
          "Escalabilidade"
        ],
        "data": [
          {
            "Sistema": "ADVTEC",
            "Faixa de PreÃ§o": "Start: R$Â 499/mÃªs (1 usuÃ¡rio); Pro: R$Â 599/mÃªs (5 usuÃ¡rios); Platinum: R$Â 999/mÃªs (10 usuÃ¡rios)",
            "Link Oficial": "advtec.com.br",
            "EspecializaÃ§Ã£o": "ğŸŸ¢ Otimizado p/ hortifrÃºti (apps para pedidos, separaÃ§Ã£o, etc)",
            "IntegraÃ§Ã£o": "ğŸŸ¢ MÃ³dulos e apps integrados (vendas, estoque, compras)",
            "Usabilidade": "ğŸŸ¢ Foco em simplicidade e rÃ¡pida implantaÃ§Ã£o (treinamentos em vÃ­deo)",
            "Suporte": "ğŸŸ¢ Suporte imediato (WhatsApp, remoto)",
            "Custo": "ğŸŸ¡ Moderado (plano Pro equivale ~R$120/usuÃ¡rio/mÃªs)",
            "Escalabilidade": "ğŸŸ¡ Escala atÃ© mÃ©dio porte (20+ usuÃ¡rios; cloud)"
          },
          {
            "Sistema": "Mercatus",
            "Faixa de PreÃ§o": "Sob consulta (plano personalizado via fornecedor; preÃ§o nÃ£o divulgado publicamente)",
            "Link Oficial": "mercatustecnologia.com.br",
            "EspecializaÃ§Ã£o": "ğŸŸ¢ Especializado em distribuidores de alimentos (30+ anos no setor hortifrÃºti)",
            "IntegraÃ§Ã£o": "ğŸŸ¢ ERP integrado â€œAPP Ceasaâ€ (mÃ³dulos compras, estoque, vendas integrados)",
            "Usabilidade": "ğŸŸ¡ Interface tradicional; possui apps mÃ³veis complementares",
            "Suporte": "ğŸŸ¢ Suporte prÃ³ximo e especializado no segmento (equipe com experiÃªncia em Ceasas)",
            "Custo": "ğŸŸ¡ MÃ©dio/Alto (soluÃ§Ã£o robusta e consolidada â€“ investimento maior)",
            "Escalabilidade": "ğŸŸ¡ Escala de mÃ©dio porte (foca em atacadistas regionais; hÃ¡ casos de sucesso no setor)"
          },
          {
            "Sistema": "WebMais",
            "Faixa de PreÃ§o": "Planos a partir de ~R$Â 250/mÃªs (Planos Ouro, Platina, Diamante; valor varia conforme usuÃ¡rios e mÃ³dulos)",
            "Link Oficial": "webmaissistemas.com.br",
            "EspecializaÃ§Ã£o": "ğŸŸ¢ Focado em indÃºstrias e distribuidoras (versÃ£o para hortifrÃºti disponÃ­vel)",
            "IntegraÃ§Ã£o": "ğŸŸ¡ ERP 100% online, integra setores bÃ¡sicos (financeiro, vendas, etc.)",
            "Usabilidade": "ğŸŸ¢ Sistema online de fÃ¡cil acesso (interface web moderna)",
            "Suporte": "ğŸŸ¢ Suporte via web/portal (empresa voltada a PMEs)",
            "Custo": "ğŸŸ¢ Baixo custo (modelo SaaS acessÃ­vel para pequenos e mÃ©dios)",
            "Escalabilidade": "ğŸŸ¡ Escalabilidade limitada a portes mÃ©dios (expansÃ£o conforme planos)"
          },
          {
            "Sistema": "NeXT Software",
            "Faixa de PreÃ§o": "Profissional: R$Â 79/mÃªs (ERP local c/ PDV, 1 usuÃ¡rio); Enterprise: R$Â 99/mÃªs (ERP completo c/ Web, 1 usuÃ¡rio) â€“ +R$Â 15-20 por usuÃ¡rio adicional",
            "Link Oficial": "nextsoftware.com.br (Hortifruti)",
            "EspecializaÃ§Ã£o": "ğŸŸ¢ VersÃ£o ERP Hortifruti dedicada (10+ anos no setor)",
            "IntegraÃ§Ã£o": "ğŸŸ¡ IntegraÃ§Ã£o bÃ¡sica; inclui PDV, NF-e/NFC-e e atÃ© marketplace (Mercado Livre)",
            "Usabilidade": "ğŸŸ¢ Interface simples com atalhos (voltada a pequenas empresas)",
            "Suporte": "ğŸŸ¢ Suporte via helpdesk, chat e tutoriais online (focado em PME)",
            "Custo": "ğŸŸ¢ Muito baixo (planos sem fidelidade e baixo custo de entrada)",
            "Escalabilidade": "ğŸ”´ Baixa â€“ ideal para pequeno porte; pode nÃ£o suportar expansÃ£o grande (limitaÃ§Ãµes de arquitetura e base local nos planos bÃ¡sicos)"
          },
          {
            "Sistema": "Limber",
            "Faixa de PreÃ§o": "Sob consulta (ERP modular, planos conforme segmento e porte da empresa)",
            "Link Oficial": "limbersoftware.com.br",
            "EspecializaÃ§Ã£o": "ğŸŸ¡ ERP agro e varejo com mÃ³dulo hortifrÃºti (Limber Agro)",
            "IntegraÃ§Ã£o": "ğŸŸ¢ IntegraÃ§Ã£o de processos operacionais e mobile (vendas, coleta, etc)",
            "Usabilidade": "ğŸŸ¡ Interface corporativa (ERP amplo para diversos segmentos)",
            "Suporte": "ğŸŸ¡ Suporte dedicado por segmento (atua com consultoria em agronegÃ³cio)",
            "Custo": "ğŸŸ¡ Custo mÃ©dio (soluÃ§Ã£o enterprise adaptada a PME e grandes)",
            "Escalabilidade": "ğŸŸ¡ Alta escalabilidade (foco em eficiÃªncia para empresas de vÃ¡rios portes)"
          },
          {
            "Sistema": "WLE Solutio",
            "Faixa de PreÃ§o": "Sob consulta (licenciamento conforme mÃ³dulos e usuÃ¡rios)",
            "Link Oficial": "wlesoft.com.br â€“ Solutio Hortifruti",
            "EspecializaÃ§Ã£o": "ğŸŸ¢ ERP Solutio Hortifruti especializado (frutas, verduras, FLV)",
            "IntegraÃ§Ã£o": "ğŸŸ¢ IntegraÃ§Ã£o de processos do fornecedor Ã  distribuiÃ§Ã£o; integra balanÃ§as e conversÃ£o unidade",
            "Usabilidade": "ğŸŸ¡ Sistema desktop com mÃ³dulos ricos (possui app mÃ³vel para pedidos)",
            "Suporte": "ğŸŸ¢ Suporte regional especializado (foco no sul; atendimento telefÃ´nico e in loco)",
            "Custo": "ğŸŸ¡ Custo mÃ©dio (soluÃ§Ã£o nichada, personalizÃ¡vel)",
            "Escalabilidade": "ğŸŸ¡ Escala para mÃ©dio porte (atende frutarias e distribuidoras regionais)"
          },
          {
            "Sistema": "TOTVS Consinco",
            "Faixa de PreÃ§o": "Sob consulta (licenÃ§a e serviÃ§os customizados â€“ soluÃ§Ã£o enterprise)",
            "Link Oficial": "consinco.com.br",
            "EspecializaÃ§Ã£o": "ğŸŸ¡ ERP de varejo/distribuiÃ§Ã£o amplo (linha Consinco, supermercados e atacado)",
            "IntegraÃ§Ã£o": "ğŸŸ¢ AltÃ­ssima integraÃ§Ã£o (ERP + WMS + PDV; mÃºltiplos mÃ³dulos e apps TOTVS)",
            "Usabilidade": "ğŸ”´ Complexidade elevada (muitas funcionalidades; exige treinamento)",
            "Suporte": "ğŸŸ¡ Suporte TOTVS (rede nacional, porÃ©m menos Ã¡gil para PME)",
            "Custo": "ğŸ”´ Alto custo (soluÃ§Ã£o robusta para grandes redes; investimento significativo)",
            "Escalabilidade": "ğŸŸ¢ AltÃ­ssima â€“ atende grandes atacadistas e redes varejistas (escalÃ¡vel para qualquer porte)"
          },
          {
            "Sistema": "Bluesoft",
            "Faixa de PreÃ§o": "A partir de ~US$Â 5.000/mÃªs (â‰ˆR$Â 25 mil) segundo Capterra (modelo 100% SaaS na nuvem)",
            "Link Oficial": "bluesoft.com.br",
            "EspecializaÃ§Ã£o": "ğŸŸ¡ ERP cloud para varejo e atacado (supermercados, distribuidoras de mÃ©dio-grande porte)",
            "IntegraÃ§Ã£o": "ğŸŸ¢ Forte integraÃ§Ã£o (API aberta; mÃ³dulos financeiros, logÃ­stica, fiscal integrados)",
            "Usabilidade": "ğŸŸ¡ Interface web moderna, porÃ©m abrangente (pode ser complexa pelo porte)",
            "Suporte": "ğŸŸ¡ Suporte dedicado a clientes enterprise (equipe especializada, TOTVS SA)",
            "Custo": "ğŸ”´ Elevado (focado em mÃ©dio/grande â€“ investimento alto mensal)",
            "Escalabilidade": "ğŸŸ¢ Alta â€“ soluÃ§Ã£o escalÃ¡vel para grandes volumes (SaaS em nuvem elÃ¡stica)"
          },
          {
            "Sistema": "",
            "Faixa de PreÃ§o": "",
            "Link Oficial": "",
            "EspecializaÃ§Ã£o": "",
            "IntegraÃ§Ã£o": "",
            "Usabilidade": "",
            "Suporte": "",
            "Custo": "",
            "Escalabilidade": ""
          },
          {
            "Sistema": "Legenda: ğŸŸ¢ = Ã³timo, ğŸŸ¡ = adequado/mediano, ğŸ”´ = fraco/limitado.",
            "Faixa de PreÃ§o": "",
            "Link Oficial": "",
            "EspecializaÃ§Ã£o": "",
            "IntegraÃ§Ã£o": "",
            "Usabilidade": "",
            "Suporte": "",
            "Custo": "",
            "Escalabilidade": ""
          }
        ]
      }
    ],
    "Comparativo 2": [
      {
        "sheet_name": "Comparativo 2",
        "rows": 7,
        "columns": 7,
        "column_names": [
          "Sistema ERP",
          "EspecializaÃ§Ã£o no Setor",
          "AutomaÃ§Ã£o & IntegraÃ§Ã£o",
          "Facilidade de Uso / ImplantaÃ§Ã£o",
          "Suporte TÃ©cnico",
          "Custo (Mensal)",
          "Escalabilidade"
        ],
        "data": [
          {
            "Sistema ERP": "ADVTEC Hortifruti",
            "EspecializaÃ§Ã£o no Setor": "100% focado em distribuidoras de hortifrÃºti (FLV). MÃ³dulos de vendas, compras, estoque, NF-e etc. jÃ¡ adaptados ao ramo.",
            "AutomaÃ§Ã£o & IntegraÃ§Ã£o": "Altamente automatizado, com mÃºltiplos apps mÃ³veis integrados (pedido de cliente, vendas, compras, picking, inventÃ¡rio). MÃ³dulos totalmente integrados (do pedido ao financeiro).",
            "Facilidade de Uso / ImplantaÃ§Ã£o": "Interface intuitiva, com fluxos pensados para FLV. ImplantaÃ§Ã£o rÃ¡pida via SaaS; fornecedor fornece vÃ­deos de treinamento e ajuda na parametrizaÃ§Ã£o inicial.",
            "Suporte TÃ©cnico": "Suporte imediato e humanizado â€“ contato direto via WhatsApp, acesso remoto e telefone. Atendimento Ã¡gil focado nos horÃ¡rios crÃ­ticos do setor.",
            "Custo (Mensal)": "Assinatura mensal (valores sob consulta). Custo acessÃ­vel para PME; personalizaÃ§Ãµes adicionais pagas Ã  parte. ROI alto com ganhos de eficiÃªncia.",
            "Escalabilidade": "Escala para pequeno e mÃ©dio porte. Suporta operaÃ§Ãµes fracionadas e atacado de FLV. Pode atender mÃºltiplos CDs regionais; para grandes redes, avaliar capacidade."
          },
          {
            "Sistema ERP": "Mercatus APP Ceasa",
            "EspecializaÃ§Ã£o no Setor": "Totalmente especializado em atacadistas/distribuidores de FLV, nasceu dentro da CEASA. Focado em vendas no atacado, boxes e distribuiÃ§Ã£o hortifrÃºti.",
            "AutomaÃ§Ã£o & IntegraÃ§Ã£o": "AutomaÃ§Ã£o elevada: apps mÃ³veis para forÃ§a de vendas (clientes fazem pedidos online) e contagem de estoque. IntegraÃ§Ã£o nativa com sistema Paripassu para rastreabilidade ANVISA. MÃ³dulos de estoque, vendas, financeiro integrados.",
            "Facilidade de Uso / ImplantaÃ§Ã£o": "Sistema em nuvem de fÃ¡cil acesso. Aplicativos amigÃ¡veis para usuÃ¡rios e clientes. ImplantaÃ§Ã£o guiada pelo fornecedor; interface moderna e simplificada.",
            "Suporte TÃ©cnico": "Suporte diferenciado, com horÃ¡rios estendidos incluindo madrugadas, fins de semana â€“ alinhado Ã  rotina de CEASA. Atendimento via telefone, WhatsApp, chat e ticket.",
            "Custo (Mensal)": "Assinatura mensal conforme mÃ³dulos. Investimento mÃ©dio; justificado pelas funcionalidades (BI, mobile) e suporte estendido. Sem custos de infraestrutura (100% cloud).",
            "Escalabilidade": "Altamente escalÃ¡vel: atende empresas em todo Brasil. Suporta crescimento de volume sem degradaÃ§Ã£o (infra AWS). Adequado a distribuidores regionais e nacionais de mÃ©dio a grande porte."
          },
          {
            "Sistema ERP": "WebMais ERP",
            "EspecializaÃ§Ã£o no Setor": "ERP nacional para Distribuidoras, com versÃ£o focada em alimentos/hortifrÃºti. Inclui mÃ³dulos de estoque, expediÃ§Ã£o, vendas, compras e financeiro ajustados para perecÃ­veis.",
            "AutomaÃ§Ã£o & IntegraÃ§Ã£o": "Boa integraÃ§Ã£o entre setores, eliminando retrabalho. Controle de lote/validade integrado ao estoque/vendas. Possui app de vendas e relatÃ³rios de rotatividade, mas automaÃ§Ã£o de picking/logÃ­stica Ã© bÃ¡sica.",
            "Facilidade de Uso / ImplantaÃ§Ã£o": "Interface web simples e em portuguÃªs. ImplementaÃ§Ã£o rÃ¡pida, com trial gratuito e suporte na migraÃ§Ã£o. Curva de aprendizado curta â€“ voltado a usuÃ¡rios de PME sem TI dedicada.",
            "Suporte TÃ©cnico": "Suporte em horÃ¡rio comercial via telefone/chat. Equipe acessÃ­vel e prestativa, porÃ©m sem suporte 24h. DocumentaÃ§Ã£o e vÃ­deos tutoriais disponÃ­veis.",
            "Custo (Mensal)": "Planos mensais acessÃ­veis (hÃ¡ opÃ§Ã£o de teste grÃ¡tis). PreÃ§o varia por nÂº de usuÃ¡rios/mÃ³dulos, porÃ©m competitivo para pequenas e mÃ©dias empresas.",
            "Escalabilidade": "Escalabilidade moderada: ideal para pequenas e mÃ©dias distribuidoras. Suporta multi-filial e volumes razoÃ¡veis. Para expansÃ£o muito grande (vÃ¡rios depÃ³sitos, milhares de notas/dia), talvez demandaria upgrade para um ERP mais robusto."
          },
          {
            "Sistema ERP": "NeXT ERP Hortifruti",
            "EspecializaÃ§Ã£o no Setor": "Desenvolvido especialmente para hortifrÃºti, com 10+ anos de melhorias no setor. Atende tanto lojas de hortifrÃºti quanto distribuidoras, com mÃ³dulos especÃ­ficos (cadastro de FLV, etc.).",
            "AutomaÃ§Ã£o & IntegraÃ§Ã£o": "Integra todos os mÃ³dulos bÃ¡sicos (compras-estoque-vendas-financeiro). EmissÃ£o ilimitada de NF-e/NFS-e. AutomaÃ§Ã£o razoÃ¡vel: gera duplicatas automaticamente, atualiza estoque em tempo real, etc., porÃ©m nÃ£o possui apps especializados (usa interface principal).",
            "Facilidade de Uso / ImplantaÃ§Ã£o": "Sistema Ã¡gil e estÃ¡vel. ImplantaÃ§Ã£o guiada com suporte da equipe NeXT; disponibiliza demo online para facilidade. UI tradicional, mas simples. UsuÃ¡rios aprendem rÃ¡pido tarefas comuns (venda, pedido, entrada).",
            "Suporte TÃ©cnico": "Suporte por telefone e chat em horÃ¡rio comercial. Equipe conhecedora do produto e do ramo, suporte personalizado para dÃºvidas fiscais/operacionais. AtualizaÃ§Ãµes frequentes para atender legislaÃ§Ã£o.",
            "Custo (Mensal)": "Mensalidade com Ã³timo custo-benefÃ­cio segundo o fornecedor. Faixas de preÃ§o para micro, pequena e mÃ©dia empresa, tornando viÃ¡vel a adesÃ£o de negÃ³cios familiares.",
            "Escalabilidade": "Escala para pequeno/mÃ©dio porte. Suporta vÃ¡rios usuÃ¡rios e filiais, mas Ã© limitado para operaÃ§Ãµes de grande porte. Permite crescimento orgÃ¢nico e aceita customizaÃ§Ãµes sob demanda se o cliente ampliar operaÃ§Ãµes."
          },
          {
            "Sistema ERP": "WLE Solutio Hortifruti",
            "EspecializaÃ§Ã£o no Setor": "ERP verticalizado para hortifrÃºti, parte da suÃ­te Solutio. Atende do varejo ao atacado de FLV, contemplando peculiaridades (un. medida, balanÃ§as, perecÃ­veis).",
            "AutomaÃ§Ã£o & IntegraÃ§Ã£o": "Altamente integrado: mÃ³dulos de compras, WMS/estoque, vendas PDV ou pedidos, financeiro e fiscal num sÃ³ sistema. Rastreamento de lotes embutido; integraÃ§Ã£o com balanÃ§as e coletores de dados; emissÃ£o de CT-e, MDF-e para logÃ­stica. AutomaÃ§Ã£o de processos avanÃ§ada (OC automÃ¡tica, atualizaÃ§Ãµes online).",
            "Facilidade de Uso / ImplantaÃ§Ã£o": "Sistema robusto, requer configuraÃ§Ã£o detalhada. ImplementaÃ§Ã£o mais longa, personalizada conforme o cliente (muitos parÃ¢metros). Interface rica em funÃ§Ãµes â€“ exige treinamento, porÃ©m fornece grande poder de gestÃ£o.",
            "Suporte TÃ©cnico": "Suporte dedicado, com consultores especializados no segmento. Atendimento humanizado, via telefone/e-mail, com direito a melhorias contÃ­nuas e backups cloud. Rede de parceiros para suporte local.",
            "Custo (Mensal)": "Modelo de licenÃ§a ou assinatura modular. Custo mÃ©dio/alto, proporcional Ã  abrangÃªncia da soluÃ§Ã£o. Recomendado para quem busca investimento em controle total (ROI via reduÃ§Ã£o de perdas e eficiÃªncia).",
            "Escalabilidade": "AltÃ­ssima escalabilidade: versÃµes para vÃ¡rios portes (Basic atÃ© Enterprise). Suporta mÃºltiplos CDs, centenas de usuÃ¡rios e grande volume de dados. Preparado para operaÃ§Ãµes complexas e em expansÃ£o, com atualizaÃ§Ãµes constantes para longevidade."
          },
          {
            "Sistema ERP": "Limber ERP (Agro)",
            "EspecializaÃ§Ã£o no Setor": "ERP nacional focado em eficiÃªncia para agronegÃ³cio e varejo. VersÃ£o hortifruti com funcionalidades dedicadas (estoque de perecÃ­veis, multi-estoques, etc.). Menos conhecido, mas especializado em melhorar gestÃ£o de FLV.",
            "AutomaÃ§Ã£o & IntegraÃ§Ã£o": "Boa integraÃ§Ã£o intersetorial: controle online de validade/lotes no estoque; mÃ³dulos de compras, estoque, vendas e financeiro unificados. Oferece requisÃ§Ã£o de compra automatizada, transferÃªncia entre estoques e inventÃ¡rio mÃ³vel.",
            "Facilidade de Uso / ImplantaÃ§Ã£o": "Interface moderna e limpa, com menus por segmento. ImplantaÃ§Ã£o assistida â€“ consultoria inicial para configurar conforme necessidades. Uso intuitivo apÃ³s setup; foco em simplicidade para o usuÃ¡rio final.",
            "Suporte TÃ©cnico": "Suporte via canais digitais e telefone. Empresa orientada a resultados do cliente â€“ acompanhamento prÃ³ximo. AtualizaÃ§Ãµes inclusas e infraestrutura cloud gerida pela Limber (menos preocupaÃ§Ã£o para TI do cliente).",
            "Custo (Mensal)": "Assinatura SaaS flexÃ­vel conforme mÃ³dulos e tamanho da empresa. Custo na faixa de ERPs cloud para PMEs; investimento se paga com ganho de controle (evitar perdas, otimizar estoque).",
            "Escalabilidade": "EscalÃ¡vel para vÃ¡rios portes: atende pequenos negÃ³cios atÃ© cooperativas e cerealistas, logo comporta distribuidoras mÃ©dias. Infraestrutura cloud ajusta recursos conforme crescimento. Pode integrar filiais e atender expansÃ£o regional sem troca de sistema."
          },
          {
            "Sistema ERP": "TOTVS (Consinco)",
            "EspecializaÃ§Ã£o no Setor": "ERP consolidado para varejo/atacado alimentar. MÃ³dulos abrangentes que cobrem hortifrÃºti (compras especializadas, gestÃ£o de fornecedores agrÃ­colas, app de compras FLV). NÃ£o exclusivo de FLV, mas altamente aderente ao setor.",
            "AutomaÃ§Ã£o & IntegraÃ§Ã£o": "IntegraÃ§Ã£o completa e personalizÃ¡vel: todos os processos de negÃ³cio em uma plataforma Ãºnica. Elevada automaÃ§Ã£o: abastecimento automÃ¡tico de estoque, geraÃ§Ã£o nativa de indicadores, integraÃ§Ã£o com PDVs, logÃ­stica (rota, CT-e) e sistemas externos via API.",
            "Facilidade de Uso / ImplantaÃ§Ã£o": "Sistema robusto e flexÃ­vel, mas complexo â€“ implementaÃ§Ã£o exige projeto estruturado e tempo. Interface profissional, requer treinamento intensivo de usuÃ¡rios-chave. Muito configurÃ¡vel Ã s regras especÃ­ficas de cada empresa.",
            "Suporte TÃ©cnico": "Suporte estruturado (TOTVS e parceiros). Atendimento via portal com SLAs; possibilidade de suporte dedicado (AMS). AtualizaÃ§Ãµes frequentes garantem compliance legal. Comunidade grande de usuÃ¡rios TOTVS para troca de conhecimento.",
            "Custo (Mensal)": "Assinatura enterprise (pode rodar on-premise ou cloud). Custo elevado, adequando-se melhor a mÃ©dias/grandes empresas. Inclui acesso a todo ecossistema TOTVS (updates, suporte, evoluÃ§Ãµes tecnolÃ³gicas).",
            "Escalabilidade": "Escalabilidade mÃ¡xima: atende redes de qualquer porte sem perda de performance. Projetado para crescer junto com a empresa â€“ multi-filial, alta volumetria, ambientes complexos. Investimento de longo prazo, evitando futuras migraÃ§Ãµes."
          }
        ]
      }
    ],
    "Comparativo 3": [
      {
        "sheet_name": "Comparativo 3",
        "rows": 8,
        "columns": 9,
        "column_names": [
          "Sistema",
          "Faixa de PreÃ§o",
          "Link Oficial",
          "EspecializaÃ§Ã£o",
          "IntegraÃ§Ã£o",
          "Usabilidade",
          "Suporte",
          "Custo",
          "Escalabilidade"
        ],
        "data": [
          {
            "Sistema": "ADVTEC",
            "Faixa de PreÃ§o": "Start: R$ 499/mÃªs (1 usuÃ¡rio)Pro: R$ 599/mÃªs (5 usuÃ¡rios)Platinum: R$ 999/mÃªs (10 usuÃ¡rios)",
            "Link Oficial": "advtec.com.br",
            "EspecializaÃ§Ã£o": "â­â­â­â­â­ Otimizado p/ hortifrÃºti (apps para pedidos, separaÃ§Ã£o, etc)",
            "IntegraÃ§Ã£o": "â­â­â­â­â­ MÃ³dulos e apps integrados (vendas, estoque, compras)",
            "Usabilidade": "â­â­â­â­â­ Foco em simplicidade e rÃ¡pida implantaÃ§Ã£o (treinamentos em vÃ­deo)",
            "Suporte": "â­â­â­â­â­ Suporte imediato (WhatsApp, remoto)",
            "Custo": "â­â­â­ Moderado (plano Pro equivale ~R$120/usuÃ¡rio/mÃªs)",
            "Escalabilidade": "â­â­â­ Escala atÃ© mÃ©dio porte (20+ usuÃ¡rios; cloud)"
          },
          {
            "Sistema": "Mercatus (APP Ceasa)",
            "Faixa de PreÃ§o": "Sob consulta (plano personalizado; preÃ§o nÃ£o divulgado)",
            "Link Oficial": "mercatustecnologia.com.br",
            "EspecializaÃ§Ã£o": "â­â­â­â­â­ Especializado em distribuidores de alimentos (30+ anos no setor hortifrÃºti)",
            "IntegraÃ§Ã£o": "â­â­â­â­â­ ERP integrado â€œAPP Ceasaâ€ (mÃ³dulos compras, estoque, vendas integrados)",
            "Usabilidade": "â­â­â­â­ Interface tradicional; possui apps mÃ³veis complementares",
            "Suporte": "â­â­â­â­â­ Suporte prÃ³ximo e especializado no segmento (equipe com experiÃªncia em CEASA)",
            "Custo": "â­â­â­ MÃ©dio/Alto (soluÃ§Ã£o robusta e consolidada â€“ investimento maior)",
            "Escalabilidade": "â­â­â­ Escala de mÃ©dio porte (foca em atacadistas regionais; hÃ¡ casos de sucesso no setor)"
          },
          {
            "Sistema": "WebMais",
            "Faixa de PreÃ§o": "A partir de ~R$ 250/mÃªs (planos Ouro, Platina, Diamante)",
            "Link Oficial": "webmaissistemas.com.br",
            "EspecializaÃ§Ã£o": "â­â­â­â­â­ Focado em indÃºstrias e distribuidoras (versÃ£o para hortifrÃºti disponÃ­vel)",
            "IntegraÃ§Ã£o": "â­â­â­ ERP 100% online, integra setores bÃ¡sicos (financeiro, vendas, etc.)",
            "Usabilidade": "â­â­â­â­â­ Sistema online de fÃ¡cil acesso (interface web moderna)",
            "Suporte": "â­â­â­â­â­ Suporte via web/portal (empresa voltada a PMEs)",
            "Custo": "â­â­â­â­â­ Baixo custo (modelo SaaS acessÃ­vel para pequenos e mÃ©dios)",
            "Escalabilidade": "â­â­â­ Escalabilidade limitada a portes mÃ©dios (expansÃ£o conforme planos)"
          },
          {
            "Sistema": "NeXT Software",
            "Faixa de PreÃ§o": "Profissional: R$ 79/mÃªs (1 usuÃ¡rio)Enterprise: R$ 99/mÃªs (1 usuÃ¡rio) + R$ 15â€“20 por usuÃ¡rio adicional",
            "Link Oficial": "nextsoftware.com.br",
            "EspecializaÃ§Ã£o": "â­â­â­â­â­ VersÃ£o ERP Hortifruti dedicada (10+ anos no setor)",
            "IntegraÃ§Ã£o": "â­â­â­ IntegraÃ§Ã£o bÃ¡sica; inclui PDV, NF-e/NFC-e e atÃ© marketplace (Mercado Livre)",
            "Usabilidade": "â­â­â­â­â­ Interface simples com atalhos (voltada a pequenas empresas)",
            "Suporte": "â­â­â­â­â­ Suporte via helpdesk, chat e tutoriais online (focado em PME)",
            "Custo": "â­â­â­â­â­ Muito baixo (planos sem fidelidade e baixo custo de entrada)",
            "Escalabilidade": "â­ Baixa â€“ ideal para pequeno porte; pode nÃ£o suportar expansÃ£o grande (limitaÃ§Ãµes de arquitetura e base local nos planos bÃ¡sicos)"
          },
          {
            "Sistema": "Limber ERP",
            "Faixa de PreÃ§o": "Sob consulta (planos modulares conforme porte/segmento)",
            "Link Oficial": "limbersoftware.com.br",
            "EspecializaÃ§Ã£o": "â­â­â­ ERP agro e varejo com mÃ³dulo hortifrÃºti (Limber Agro)",
            "IntegraÃ§Ã£o": "â­â­â­â­â­ IntegraÃ§Ã£o de processos operacionais e mobile (vendas, coleta, etc)",
            "Usabilidade": "â­â­â­ Interface corporativa (ERP amplo para diversos segmentos)",
            "Suporte": "â­â­â­ Suporte dedicado por segmento (atua com consultoria em agronegÃ³cio)",
            "Custo": "â­â­â­ Custo mÃ©dio (soluÃ§Ã£o enterprise adaptada a PME e grandes)",
            "Escalabilidade": "â­â­â­ Alta escalabilidade (foco em eficiÃªncia para empresas de vÃ¡rios portes)"
          },
          {
            "Sistema": "WLE Solutio (Hortifruti)",
            "Faixa de PreÃ§o": "Sob consulta (licenciamento modular conforme usuÃ¡rios/mÃ³dulos)",
            "Link Oficial": "wlesoft.com.br â€“ Solutio Hortifruti",
            "EspecializaÃ§Ã£o": "â­â­â­â­â­ ERP Solutio Hortifruti especializado (frutas, verduras, FLV)",
            "IntegraÃ§Ã£o": "â­â­â­â­â­ IntegraÃ§Ã£o de processos do fornecedor Ã  distribuiÃ§Ã£o ; integra balanÃ§as e conversÃ£o unidade",
            "Usabilidade": "â­â­â­ Sistema desktop com mÃ³dulos ricos (possui app mÃ³vel para pedidos)",
            "Suporte": "â­â­â­â­â­ Suporte regional especializado (foco no Sul; atendimento telefÃ´nico e in loco)",
            "Custo": "â­â­â­ Custo mÃ©dio (soluÃ§Ã£o nichada, personalizÃ¡vel)",
            "Escalabilidade": "â­â­â­ Escala para mÃ©dio porte (atende frutarias e distribuidoras regionais)"
          },
          {
            "Sistema": "TOTVS (Consinco)",
            "Faixa de PreÃ§o": "Sob consulta (licenÃ§a e serviÃ§os customizados; soluÃ§Ã£o enterprise)",
            "Link Oficial": "consinco.com.br",
            "EspecializaÃ§Ã£o": "â­â­â­ ERP de varejo/distribuiÃ§Ã£o amplo (linha Consinco, supermercados e atacado)",
            "IntegraÃ§Ã£o": "â­â­â­â­â­ AltÃ­ssima integraÃ§Ã£o (ERP + WMS + PDV; mÃºltiplos mÃ³dulos e apps TOTVS)",
            "Usabilidade": "â­ Complexidade elevada (muitas funcionalidades; exige treinamento)",
            "Suporte": "â­â­â­ Suporte TOTVS (rede nacional, porÃ©m menos Ã¡gil para PME)",
            "Custo": "â­ Alto custo (soluÃ§Ã£o robusta para grandes redes; investimento significativo)",
            "Escalabilidade": "â­â­â­â­â­ AltÃ­ssima â€“ atende grandes atacadistas e redes varejistas (escalÃ¡vel para qualquer porte)"
          },
          {
            "Sistema": "Bluesoft",
            "Faixa de PreÃ§o": "A partir de ~US$ 5.000/mÃªs (~R$ 25 000/mÃªs)",
            "Link Oficial": "bluesoft.com.br",
            "EspecializaÃ§Ã£o": "â­â­â­ ERP cloud para varejo e atacado (supermercados, distribuidoras de mÃ©dio-grande porte)",
            "IntegraÃ§Ã£o": "â­â­â­â­â­ Forte integraÃ§Ã£o (API aberta; mÃ³dulos financeiros, logÃ­stica, fiscal integrados)",
            "Usabilidade": "â­â­â­ Interface web moderna, porÃ©m abrangente (pode ser complexa pelo porte)",
            "Suporte": "â­â­â­ Suporte dedicado a clientes enterprise (equipe especializada TOTVS SA)",
            "Custo": "â­ Elevado (focado em mÃ©dio/grande â€“ investimento alto mensal)",
            "Escalabilidade": "â­â­â­â­â­ Alta â€“ soluÃ§Ã£o escalÃ¡vel para grandes volumes (SaaS em nuvem elÃ¡stica)"
          }
        ]
      }
    ],
    "Comparativo 4": [
      {
        "sheet_name": "Comparativo 4",
        "rows": 6,
        "columns": 10,
        "column_names": [
          "Sistema",
          "Link Oficial",
          "Faixa de PreÃ§o",
          "EspecializaÃ§Ã£o",
          "IntegraÃ§Ã£o",
          "Usabilidade",
          "Suporte",
          "Custo",
          "Escalabilidade",
          "InovaÃ§Ã£o TecnolÃ³gica"
        ],
        "data": [
          {
            "Sistema": "ADVTEC",
            "Link Oficial": "advtec.com.br",
            "Faixa de PreÃ§o": "Start: R$ 399/mÃªsPro: R$ 599/mÃªsPlatinum: R$ 999/mÃªs",
            "EspecializaÃ§Ã£o": "â˜…â˜…â˜…â˜…â˜… (Foco 100 % em hortifrÃºti, apps exclusivos)",
            "IntegraÃ§Ã£o": "â˜…â˜…â˜…â˜…â˜† (NF-e, balanÃ§as, integraÃ§Ãµes padrÃµes)",
            "Usabilidade": "â˜…â˜…â˜…â˜…â˜… (Muito intuitivo, mobile-first)",
            "Suporte": "â˜…â˜…â˜…â˜…â˜… (Suporte imediato via WhatsApp)",
            "Custo": "â˜…â˜…â˜…â˜…â˜† (PreÃ§o acessÃ­vel)",
            "Escalabilidade": "â˜…â˜…â˜…â˜…â˜† (Cresce bem para PMEs, cloud)",
            "InovaÃ§Ã£o TecnolÃ³gica": "â˜…â˜…â˜…â˜…â˜… (IA em pedidos, suite mobile completa)"
          },
          {
            "Sistema": "Mercatus (APP Ceasa)",
            "Link Oficial": "mercatustecnologia.com.br",
            "Faixa de PreÃ§o": "Sob consulta (plano personalizado)",
            "EspecializaÃ§Ã£o": "â˜…â˜…â˜…â˜…â˜… (30 anos no setor FLV, recursos Ceasa)",
            "IntegraÃ§Ã£o": "â˜…â˜…â˜…â˜…â˜… (MÃ³dulos integrados, Paripassu, bancÃ¡ria)",
            "Usabilidade": "â˜…â˜…â˜…â˜…â˜† (Sistema robusto, apps ajudam)",
            "Suporte": "â˜…â˜…â˜…â˜…â˜… (Suporte estendido em horÃ¡rios crÃ­ticos)",
            "Custo": "â˜…â˜…â˜…â˜†â˜† (Investimento mÃ©dio/alto)",
            "Escalabilidade": "â˜…â˜…â˜…â˜…â˜† (Escala para mÃ©dias, cloud)",
            "InovaÃ§Ã£o TecnolÃ³gica": "â˜…â˜…â˜…â˜…â˜† (BI, mobile, rastreabilidade)"
          },
          {
            "Sistema": "HortiGestÃ£o",
            "Link Oficial": "hortigestao.com.br",
            "Faixa de PreÃ§o": "Planos a partir de ~R$ 299/mÃªs",
            "EspecializaÃ§Ã£o": "â˜…â˜…â˜…â˜…â˜… (Nativo de CEASA, rotina FLV)",
            "IntegraÃ§Ã£o": "â˜…â˜…â˜…â˜…â˜† (NF-e, boletos, bÃ¡sico contÃ¡bil)",
            "Usabilidade": "â˜…â˜…â˜…â˜…â˜… (Fluxo otimizado, app fÃ¡cil)",
            "Suporte": "â˜…â˜…â˜…â˜…â˜… (Suporte 24 h, proximidade)",
            "Custo": "â˜…â˜…â˜…â˜…â˜† (SaaS, bom custo-benefÃ­cio)",
            "Escalabilidade": "â˜…â˜…â˜…â˜…â˜† (Cloud puro, multiusuÃ¡rio)",
            "InovaÃ§Ã£o TecnolÃ³gica": "â˜…â˜…â˜…â˜…â˜† (App mÃ³vel, relatÃ³rios inteligentes)"
          },
          {
            "Sistema": "POST Sistemas",
            "Link Oficial": "postsistemas.com.br",
            "Faixa de PreÃ§o": "Sob consulta (modular)",
            "EspecializaÃ§Ã£o": "â˜…â˜…â˜…â˜…â˜† (ERP multi-segmento com mÃ³dulo FLV)",
            "IntegraÃ§Ã£o": "â˜…â˜…â˜…â˜…â˜… (Paripassu, TEF, NF-e, contÃ¡bil)",
            "Usabilidade": "â˜…â˜…â˜…â˜…â˜† (Interface tradicional + apps)",
            "Suporte": "â˜…â˜…â˜…â˜…â˜… (Suporte dedicado, melhorias)",
            "Custo": "â˜…â˜…â˜…â˜†â˜† (Modular, varia conforme extras)",
            "Escalabilidade": "â˜…â˜…â˜…â˜…â˜… (Altamente escalÃ¡vel)",
            "InovaÃ§Ã£o TecnolÃ³gica": "â˜…â˜…â˜…â˜…â˜† (ForÃ§a de vendas/compras mobile, rastreabilidade)"
          },
          {
            "Sistema": "WLE Solutio Hortifruti",
            "Link Oficial": "wlesoft.com.br",
            "Faixa de PreÃ§o": "Sob consulta (licenciamento modular)",
            "EspecializaÃ§Ã£o": "â˜…â˜…â˜…â˜…â˜† (ERP moldÃ¡vel para FLV e varejo)",
            "IntegraÃ§Ã£o": "â˜…â˜…â˜…â˜…â˜… (Integr. balanÃ§as, SAT, NF-e, contÃ¡bil)",
            "Usabilidade": "â˜…â˜…â˜…â˜…â˜† (Uso simples, PDV integrado)",
            "Suporte": "â˜…â˜…â˜…â˜…â˜† (Suporte regional, parceiros locais)",
            "Custo": "â˜…â˜…â˜…â˜…â˜† (Modular, custo mÃ©dio)",
            "Escalabilidade": "â˜…â˜…â˜…â˜…â˜† (Bom para pequenas e mÃ©dias)",
            "InovaÃ§Ã£o TecnolÃ³gica": "â˜…â˜…â˜…â˜…â˜† (Etiquetagem, mobile inventory)"
          },
          {
            "Sistema": "Limber Agro",
            "Link Oficial": "limbersoftware.com.br",
            "Faixa de PreÃ§o": "Sob consulta (plano modular)",
            "EspecializaÃ§Ã£o": "â˜…â˜…â˜…â˜…â˜† (AgronegÃ³cio + mÃ³dulo FLV)",
            "IntegraÃ§Ã£o": "â˜…â˜…â˜…â˜…â˜… (Cadeias agrÃ­colas, BI, IoT)",
            "Usabilidade": "â˜…â˜…â˜…â˜†â˜† (Exige capacitaÃ§Ã£o)",
            "Suporte": "â˜…â˜…â˜…â˜…â˜† (Suporte completo, consultoria)",
            "Custo": "â˜…â˜…â˜†â˜†â˜† (Custo elevado, foco enterprise)",
            "Escalabilidade": "â˜…â˜…â˜…â˜…â˜… (Nuvem escalÃ¡vel, grande volume)",
            "InovaÃ§Ã£o TecnolÃ³gica": "â˜…â˜…â˜…â˜…â˜… (RoteirizaÃ§Ã£o automÃ¡tica, IA)"
          }
        ]
      }
    ]
  },
  "docling_tables": [],
  "metadata": {
    "num_sheets": 4,
    "sheet_names": [
      "Comparativo 1",
      "Comparativo 2",
      "Comparativo 3",
      "Comparativo 4"
    ],
    "sheets_info": {
      "Comparativo 1": {
        "rows": 10,
        "columns": 9,
        "column_names": [
          "Sistema",
          "Faixa de PreÃ§o",
          "Link Oficial",
          "EspecializaÃ§Ã£o",
          "IntegraÃ§Ã£o",
          "Usabilidade",
          "Suporte",
          "Custo",
          "Escalabilidade"
        ],
        "has_data": true
      },
      "Comparativo 2": {
        "rows": 7,
        "columns": 7,
        "column_names": [
          "Sistema ERP",
          "EspecializaÃ§Ã£o no Setor",
          "AutomaÃ§Ã£o & IntegraÃ§Ã£o",
          "Facilidade de Uso / ImplantaÃ§Ã£o",
          "Suporte TÃ©cnico",
          "Custo (Mensal)",
          "Escalabilidade"
        ],
        "has_data": true
      },
      "Comparativo 3": {
        "rows": 8,
        "columns": 9,
        "column_names": [
          "Sistema",
          "Faixa de PreÃ§o",
          "Link Oficial",
          "EspecializaÃ§Ã£o",
          "IntegraÃ§Ã£o",
          "Usabilidade",
          "Suporte",
          "Custo",
          "Escalabilidade"
        ],
        "has_data": true
      },
      "Comparativo 4": {
        "rows": 6,
        "columns": 10,
        "column_names": [
          "Sistema",
          "Link Oficial",
          "Faixa de PreÃ§o",
          "EspecializaÃ§Ã£o",
          "IntegraÃ§Ã£o",
          "Usabilidade",
          "Suporte",
          "Custo",
          "Escalabilidade",
          "InovaÃ§Ã£o TecnolÃ³gica"
        ],
        "has_data": true
      }
    },
    "num_pages": 4
  }
}